hawkrest/__init__.py
hawkrest/middleware.py
hawkrest/models.py
hawkrest/util.py
hawkrest/management/__init__.py
hawkrest/management/commands/__init__.py
hawkrest/management/commands/hawkrequest.py
hawkrest-1.0.1.dist-info/LICENSE.txt
hawkrest-1.0.1.dist-info/METADATA
hawkrest-1.0.1.dist-info/WHEEL
hawkrest-1.0.1.dist-info/top_level.txt
hawkrest-1.0.1.dist-info/RECORD
