Metadata-Version: 2.1
Name: hawkrest
Version: 1.0.1
Summary: Hawk HTTP Authorization for Django Rest Framework
Home-page: https://github.com/kumar303/hawkrest
Author: Kumar McMillan
Author-email: kumar.mcmillan@gmail.com
License: MPL 2.0 (Mozilla Public License)
Platform: UNKNOWN
Classifier: Framework :: Django
Classifier: Intended Audience :: Developers
Classifier: Natural Language :: English
Classifier: Operating System :: OS Independent
Classifier: Programming Language :: Python :: 2
Classifier: Programming Language :: Python :: 3
Classifier: Programming Language :: Python :: 2.7
Classifier: Programming Language :: Python :: 3.4
Classifier: Programming Language :: Python :: 3.5
Classifier: Programming Language :: Python :: 3.6
Classifier: Topic :: Internet :: WWW/HTTP
Requires-Dist: djangorestframework
Requires-Dist: mohawk (>=0.3.4)
